kagiso_image/__init__.py
kagiso_image/constants.py
kagiso_image/exceptions.py
kagiso_image/models.py
kagiso_image/utils.py
kagiso_image/migrations/0001_initial.py
kagiso_image/migrations/0002_auto_20160322_1251.py
kagiso_image/migrations/0003_auto_20160809_1655.py
kagiso_image/migrations/0004_auto_20170202_0213.py
kagiso_image/migrations/0005_auto_20170203_0409.py
kagiso_image/migrations/0006_auto_20170203_0417.py
kagiso_image/migrations/0007_remove_imagewithattributionrendition_filter.py
kagiso_image/migrations/__init__.py
kagiso_image/settings/__init__.py
kagiso_image/settings/test.py
kagiso_image/tests/__init__.py
kagiso_image/tests/test_models.py
kagiso_image/tests/test_utils.py
kagiso_image-3.0.3.post0.dist-info/METADATA
kagiso_image-3.0.3.post0.dist-info/WHEEL
kagiso_image-3.0.3.post0.dist-info/top_level.txt
kagiso_image-3.0.3.post0.dist-info/RECORD
