Metadata-Version: 2.1
Name: kagiso-image
Version: 3.0.3.post0
Summary: Kagiso Image with Attribution
Home-page: https://github.com/Kagiso-Future-Media/kagiso_image
Author: Kagiso Media
Author-email: development@kagiso.io
License: UNKNOWN
Platform: UNKNOWN
Requires-Dist: wagtail (>=1.8.0)
